infinity_ml/__init__.py
infinity_ml/client.py
infinity_ml/models.py
infinity_ml/py.typed
infinity_ml-0.2.2.dist-info/licenses/LICENSE
infinity_ml-0.2.2.dist-info/METADATA
infinity_ml-0.2.2.dist-info/WHEEL
infinity_ml-0.2.2.dist-info/top_level.txt
infinity_ml-0.2.2.dist-info/RECORD
