Metadata-Version: 2.4
Name: infinity-ml
Version: 0.2.2
Summary: Python client for Infinity Media Server - GPU-accelerated image, video, and audio generation
Author: Infinity AI Institute
License-Expression: MIT
Project-URL: Homepage, https://infinity.inc
Project-URL: Repository, https://github.com/infinity-ai-institute/infinity-sdk
Project-URL: Documentation, https://github.com/infinity-ai-institute/infinity-sdk/tree/main/sdk-py
Project-URL: Changelog, https://github.com/infinity-ai-institute/infinity-sdk/blob/main/sdk-py/CHANGELOG.md
Keywords: ai,gpu,image-generation,video-generation,text-to-speech,flux,diffusion,infinity-ml
Classifier: Development Status :: 3 - Alpha
Classifier: Intended Audience :: Developers
Classifier: Programming Language :: Python :: 3
Classifier: Programming Language :: Python :: 3.10
Classifier: Programming Language :: Python :: 3.11
Classifier: Programming Language :: Python :: 3.12
Classifier: Topic :: Scientific/Engineering :: Artificial Intelligence
Requires-Python: >=3.10
License-File: LICENSE
Requires-Dist: httpx>=0.25.0
Provides-Extra: dev
Requires-Dist: pytest>=7.0.0; extra == "dev"
Requires-Dist: pytest-asyncio>=0.21.0; extra == "dev"
Requires-Dist: ruff>=0.1.0; extra == "dev"
Requires-Dist: pyright>=1.1.0; extra == "dev"
Dynamic: license-file
